{
  "persyaratan": [
    {
      "id": 5,
      "namaPersyaratan": "Nama",
      "tipeData": "String",
      "length": "255"
    },
    {
      "id": 6,
      "namaPersyaratan": "Tanggal Lahir",
      "tipeData": "Date",
      "length": "dd/mm/yyy"
    }
  ],
  "dikembalikan": [
    {
      "id": 1,
      "username": "Miftah",
      "judul": "Enak Nya Menjadi Programmer",
      "tanggal": "22/11/2021",
      "jenis": "Event"
    }
  ],
  "published": [
    {
      "id": 1,
      "username": "Faiz",
      "judul": "Enak Nya Menjadi Seorang Komunis",
      "tanggal": "22/11/2021",
      "jenis": "Event"
    }
  ]
}